image.py
cImage-2.0.2.dist-info/METADATA
cImage-2.0.2.dist-info/WHEEL
cImage-2.0.2.dist-info/top_level.txt
cImage-2.0.2.dist-info/RECORD
